LICENSE
MANIFEST.in
README.md
build.sh
go.mod
go.sum
setup.py
e2e_test/__init__.py
e2e_test/test_built_lib.py
goodbc_python/__init__.py
goodbc_python/common.py
goodbc_python/db_api.py
goodbc_python/rpc_session.py
goodbc_python/rpc_session_test.py
goodbc_python.egg-info/PKG-INFO
goodbc_python.egg-info/SOURCES.txt
goodbc_python.egg-info/dependency_links.txt
goodbc_python.egg-info/not-zip-safe
goodbc_python.egg-info/requires.txt
goodbc_python.egg-info/top_level.txt
goodbc_python/py2/Makefile
goodbc_python/py2/__init__.py
goodbc_python/py2/build.py
goodbc_python/py2/go.py
goodbc_python/py2/goodbc_python_go.c
goodbc_python/py2/goodbc_python_go.go
goodbc_python/py2/goodbc_python_go.py
goodbc_python/py2/goodbc_python_go_go.h
goodbc_python/py2/goodbc_python_go_go.so
goodbc_python_go/rpc.go
goodbc_python_go/session.go
goodbc_python_go/utils.go
goodbc_python_go/utils_test.go