Metadata-Version: 2.1
Name: goodbc-python
Version: 0.91
Summary: GoODBC Python
Home-page: https://github.com/ftpsolutions/goodbc-python
Author: Edward @ FTP Technologies
Author-email: edward.beech@ftpsolutions.com.au
License: MIT
Platform: UNKNOWN
Classifier: Development Status :: 7 - Inactive
Classifier: Intended Audience :: Developers
Classifier: Programming Language :: Python :: 2.7
Classifier: Operating System :: POSIX
Classifier: Operating System :: Unix
Classifier: Operating System :: MacOS
